{"info":{"_postman_id":"6675a76e-fa30-421e-8b96-2d66d52adca8","name":"MASKAWASUB API DOCUMENTATION ","description":"<html><head></head><body><p>MASKAWASUB API Doc Get your Token here <a href=\"https://www.maskawasub.com/documentation/\">https://www.maskawasub.com/documentation/</a></p>\n</body></html>","schema":"https://schema.getpostman.com/json/collection/v2.0.0/collection.json","toc":[],"owner":"14036001","collectionId":"6675a76e-fa30-421e-8b96-2d66d52adca8","publishedId":"UV5UiJ4E","public":true,"customColor":{"top-bar":"FFFFFF","right-sidebar":"303030","highlight":"EF5B25"},"publishDate":"2021-10-13T18:11:38.000Z"},"item":[{"name":"Check User Details","id":"179d3f2b-4b40-4c29-a44e-251709a301d1","protocolProfileBehavior":{"disableBodyPruning":true},"request":{"auth":{"type":"apikey","apikey":{"basicConfig":[{"key":"key","value":"Authorization"},{"key":"value","value":"<value>"}]},"isInherited":false},"method":"GET","header":[{"warning":"This is a duplicate header and will be overridden by the Authorization header generated by Postman.","key":"Authorization","value":"Token 66f2e5c39ac8640f13cd888f161385b12f7e5e92","type":"text"},{"key":"Content-Type","value":"application/json","type":"text"}],"url":"https://www.maskawasub.com/api/user/","urlObject":{"protocol":"https","path":["api","user",""],"host":["www","maskawasub","com"],"query":[],"variable":[]}},"response":[],"_postman_id":"179d3f2b-4b40-4c29-a44e-251709a301d1"},{"name":"Buy Data","id":"e6e1ebd4-7fa4-4051-a1d1-67c8d44f2820","protocolProfileBehavior":{"disableBodyPruning":true},"request":{"auth":{"type":"apikey","apikey":{"basicConfig":[{"key":"key","value":"Authorization"},{"key":"value","value":"<value>"}]},"isInherited":false},"method":"POST","header":[{"warning":"This is a duplicate header and will be overridden by the Authorization header generated by Postman.","key":"Authorization","value":"Token 66f2e5c39ac8640f13cd888f161385b12f7e5e92","type":"text"},{"key":"Content-Type","value":"application/json","type":"text"}],"body":{"mode":"raw","raw":"{\"network\":network_id,\r\n\"mobile_number\": \"09095263835\",\r\n\"plan\": plan_id,\r\n\"Ported_number\":true\r\n}"},"url":"https://www.maskawasub.com/api/data/","urlObject":{"protocol":"https","path":["api","data",""],"host":["www","maskawasub","com"],"query":[],"variable":[]}},"response":[],"_postman_id":"e6e1ebd4-7fa4-4051-a1d1-67c8d44f2820"},{"name":"Buy E-pins/Result checker","id":"a6a50747-4a64-4d1f-b288-ee6973011efa","protocolProfileBehavior":{"disableBodyPruning":true},"request":{"auth":{"type":"apikey","apikey":{"basicConfig":[{"key":"key","value":"Authorization"},{"key":"value","value":"<value>"}]},"isInherited":false},"method":"POST","header":[{"warning":"This is a duplicate header and will be overridden by the Authorization header generated by Postman.","key":"Authorization","value":"Token 66f2e5c39ac8640f13cd888f161385b12f7e5e92","type":"text"},{"key":"Content-Type","value":"application/json","type":"text"}],"body":{"mode":"raw","raw":"{\"exam_name\": \"exam_name\",\r\n\"quantity\": \"1\"\r\n}"},"url":"https://www.maskawasub.com/api/epin/","urlObject":{"protocol":"https","path":["api","epin",""],"host":["www","maskawasub","com"],"query":[],"variable":[]}},"response":[],"_postman_id":"a6a50747-4a64-4d1f-b288-ee6973011efa"},{"name":"Get All Data Transactions","id":"93220162-fa11-49e9-ab3d-ca7765a4ffb3","protocolProfileBehavior":{"disableBodyPruning":true},"request":{"auth":{"type":"apikey","apikey":{"basicConfig":[{"key":"key","value":"Authorization"},{"key":"value","value":"<value>"}]},"isInherited":false},"method":"GET","header":[],"url":"https://www.maskawasub.com/api/data/","urlObject":{"protocol":"https","path":["api","data",""],"host":["www","maskawasub","com"],"query":[],"variable":[]}},"response":[],"_postman_id":"93220162-fa11-49e9-ab3d-ca7765a4ffb3"},{"name":"Query Dat Transaction","id":"a72bae09-3df3-45e6-af62-c2f654b15bcb","protocolProfileBehavior":{"disableBodyPruning":true},"request":{"auth":{"type":"apikey","apikey":{"basicConfig":[{"key":"key","value":"Authorization"},{"key":"value","value":"<value>"}]},"isInherited":false},"method":"GET","header":[],"url":"https://www.maskawasub.com/api/data/58","urlObject":{"protocol":"https","path":["api","data","58"],"host":["www","maskawasub","com"],"query":[],"variable":[]}},"response":[],"_postman_id":"a72bae09-3df3-45e6-af62-c2f654b15bcb"},{"name":"Buy Airtime TopUp and Get all Airtime Transaction","id":"f3ef8bcd-b0ec-4dae-821b-7459ea5e5e5b","protocolProfileBehavior":{"disableBodyPruning":true},"request":{"auth":{"type":"apikey","apikey":{"basicConfig":[{"key":"key","value":"Authorization"},{"key":"value","value":"<value>"}]},"isInherited":false},"method":"POST","header":[{"warning":"This is a duplicate header and will be overridden by the Authorization header generated by Postman.","key":"Authorization","value":"Token 66f2e5c39ac8640f13cd888f161385b12f7e5e92","type":"text"},{"key":"Content-Type","value":"application/json","type":"text"}],"body":{"mode":"raw","raw":"{\"network\":network_id,\r\n\"amount\":amount,\r\n\"mobile_number\":phone,\r\n\"Ported_number\":true\r\n\"airtime_type\":\"VTU\"\r\n\r\n}"},"url":"https://www.maskawasub.com/api/topup/","urlObject":{"protocol":"https","path":["api","topup",""],"host":["www","maskawasub","com"],"query":[],"variable":[]}},"response":[],"_postman_id":"f3ef8bcd-b0ec-4dae-821b-7459ea5e5e5b"},{"name":"Query Airtime Transaction ","id":"4ad8e321-f452-47e9-aa13-3298de550997","protocolProfileBehavior":{"disableBodyPruning":true},"request":{"auth":{"type":"apikey","apikey":{"basicConfig":[{"key":"key","value":"Authorization"},{"key":"value","value":"<value>"}]},"isInherited":false},"method":"GET","header":[{"warning":"This is a duplicate header and will be overridden by the Authorization header generated by Postman.","key":"Authorization","value":"Token 66f2e5c39ac8640f13cd888f161385b12f7e5e92","type":"text"},{"key":"Content-Type","value":"application/json","type":"text"}],"url":"https://www.maskawasub.com/api/data/id","urlObject":{"protocol":"https","path":["api","data","id"],"host":["www","maskawasub","com"],"query":[],"variable":[]}},"response":[],"_postman_id":"4ad8e321-f452-47e9-aa13-3298de550997"},{"name":"Buy Electricity Bill Payment and Get all Transaction","id":"2f592432-c7e5-428c-a81e-5d6ec707e1f8","protocolProfileBehavior":{"disableBodyPruning":true},"request":{"auth":{"type":"apikey","apikey":{"basicConfig":[{"key":"key","value":"Authorization"},{"key":"value","value":"<value>"}]},"isInherited":false},"method":"POST","header":[{"warning":"This is a duplicate header and will be overridden by the Authorization header generated by Postman.","key":"Authorization","value":"Token 66f2e5c39ac8640f13cd888f161385b12f7e5e92","type":"text"},{"key":"Content-Type","value":"application/json","type":"text"}],"body":{"mode":"raw","raw":"{\"disco_name\":disco,\r\n\"amount\":amount to pay,\r\n\"meter_number\": meter number,\r\n\"MeterType\": meter type id (PREPAID:1,POSTPAID:2)\r\n\r\n}"},"url":"https://www.maskawasub.com/api/billpayment/","urlObject":{"protocol":"https","path":["api","billpayment",""],"host":["www","maskawasub","com"],"query":[],"variable":[]}},"response":[],"_postman_id":"2f592432-c7e5-428c-a81e-5d6ec707e1f8"},{"name":"Query Bill Payment","id":"631daa0d-d796-493a-8740-334145beb513","protocolProfileBehavior":{"disableBodyPruning":true},"request":{"auth":{"type":"apikey","apikey":{"basicConfig":[{"key":"key","value":"Authorization"},{"key":"value","value":"<value>"}]},"isInherited":false},"method":"GET","header":[{"warning":"This is a duplicate header and will be overridden by the Authorization header generated by Postman.","key":"Authorization","value":"Token 66f2e5c39ac8640f13cd888f161385b12f7e5e92","type":"text"}],"url":"https://www.maskawasub.com/api/billpayment/id","urlObject":{"protocol":"https","path":["api","billpayment","id"],"host":["www","maskawasub","com"],"query":[],"variable":[]}},"response":[],"_postman_id":"631daa0d-d796-493a-8740-334145beb513"},{"name":"Buy Cable and get all transaction","id":"8d63ff12-5b86-4874-a78d-4565de1cfa8f","protocolProfileBehavior":{"disableBodyPruning":true},"request":{"auth":{"type":"apikey","apikey":{"basicConfig":[{"key":"key","value":"Authorization"},{"key":"value","value":"<value>"}]},"isInherited":false},"method":"POST","header":[{"warning":"This is a duplicate header and will be overridden by the Authorization header generated by Postman.","key":"Authorization","value":"Token 66f2e5c39ac8640f13cd888f161385b12f7e5e92","type":"text"},{"key":"Content-Type","value":"application/json","type":"text"}],"body":{"mode":"raw","raw":"{\r\n    \"cablename\":cablename id,\r\n    \"cableplan\": cableplan id,\r\n    \"smart_card_number\": meter\r\n}"},"url":"https://www.maskawasub.com/api/cablesub/","urlObject":{"protocol":"https","path":["api","cablesub",""],"host":["www","maskawasub","com"],"query":[],"variable":[]}},"response":[],"_postman_id":"8d63ff12-5b86-4874-a78d-4565de1cfa8f"},{"name":"Query Cablesub","id":"4197de58-538a-448f-ae34-7040a3787643","protocolProfileBehavior":{"disableBodyPruning":true},"request":{"auth":{"type":"apikey","apikey":{"basicConfig":[{"key":"key","value":"Authorization"},{"key":"value","value":"<value>"}]},"isInherited":false},"method":"GET","header":[{"warning":"This is a duplicate header and will be overridden by the Authorization header generated by Postman.","key":"Authorization","value":"Token 66f2e5c39ac8640f13cd888f161385b12f7e5e92","type":"text"},{"key":"Content-Type","value":"application/json","type":"text"}],"url":"https://www.maskawasub.com/api/cablesub/id","urlObject":{"protocol":"https","path":["api","cablesub","id"],"host":["www","maskawasub","com"],"query":[],"variable":[]}},"response":[],"_postman_id":"4197de58-538a-448f-ae34-7040a3787643"},{"name":"Validate IUC","id":"f5f6e03f-a541-41f2-afae-4f73259d314c","protocolProfileBehavior":{"disableBodyPruning":true},"request":{"auth":{"type":"apikey","apikey":{"basicConfig":[{"key":"key","value":"Authorization"},{"key":"value","value":"<value>"}]},"isInherited":false},"method":"GET","header":[{"warning":"This is a duplicate header and will be overridden by the Authorization header generated by Postman.","key":"Authorization","value":"Token 66f2e5c39ac8640f13cd888f161385b12f7e5e92","type":"text"},{"key":"Content-Type","value":"application/json","type":"text"}],"url":"https://www.maskawasub.com/api/validateiuc?smart_card_number=iuc& &cablename=id","urlObject":{"protocol":"https","path":["api","validateiuc"],"host":["www","maskawasub","com"],"query":[{"key":"smart_card_number","value":"iuc"},{"key":" ","value":null},{"key":"cablename","value":"id"}],"variable":[]}},"response":[],"_postman_id":"f5f6e03f-a541-41f2-afae-4f73259d314c"},{"name":"Validate Meter","id":"17d5cd7e-d912-4988-9203-57f06b0300e8","protocolProfileBehavior":{"disableBodyPruning":true},"request":{"auth":{"type":"apikey","apikey":{"basicConfig":[{"key":"key","value":"Authorization"},{"key":"value","value":"<value>"}]},"isInherited":false},"method":"GET","header":[{"warning":"This is a duplicate header and will be overridden by the Authorization header generated by Postman.","key":"Authorization","value":"Token 66f2e5c39ac8640f13cd888f161385b12f7e5e92","type":"text"},{"key":"Content-Type","value":"application/json","type":"text"}],"url":"https://www.maskawasub.com/api/validatemeter?meternumber=meter& &disconame=id& &mtype=metertype","urlObject":{"protocol":"https","path":["api","validatemeter"],"host":["www","maskawasub","com"],"query":[{"key":"meternumber","value":"meter"},{"key":" ","value":null},{"key":"disconame","value":"id"},{"key":" ","value":null},{"key":"mtype","value":"metertype"}],"variable":[]}},"response":[],"_postman_id":"17d5cd7e-d912-4988-9203-57f06b0300e8"},{"name":"Get All Data Transactions Copy","id":"1728611c-c56c-4180-8a81-c11b3c2838d7","protocolProfileBehavior":{"disableBodyPruning":true},"request":{"auth":{"type":"apikey","apikey":{"basicConfig":[{"key":"key","value":"Authorization"},{"key":"value","value":"<value>"}]},"isInherited":false},"method":"GET","header":[],"url":"https://www.smartspeedtelecom.com/api/data/","urlObject":{"protocol":"https","path":["api","data",""],"host":["www","smartspeedtelecom","com"],"query":[],"variable":[]}},"response":[],"_postman_id":"1728611c-c56c-4180-8a81-c11b3c2838d7"},{"name":"Get All Data Transactions Copy","id":"20e24401-5b38-42cb-84cd-8281ac8e05ec","protocolProfileBehavior":{"disableBodyPruning":true},"request":{"auth":{"type":"apikey","apikey":{"basicConfig":[{"key":"key","value":"Authorization"},{"key":"value","value":"<value>"}]},"isInherited":false},"method":"GET","header":[],"url":"https://www.maskawasub.com/api/data/","urlObject":{"protocol":"https","path":["api","data",""],"host":["www","maskawasub","com"],"query":[],"variable":[]}},"response":[],"_postman_id":"20e24401-5b38-42cb-84cd-8281ac8e05ec"}],"auth":{"type":"apikey","apikey":{"basicConfig":[{"key":"key","value":"Authorization"},{"key":"value","value":"<value>"}]}},"event":[{"listen":"prerequest","script":{"id":"65a6fb11-1769-4d75-b96a-8b61b0458d33","type":"text/javascript","exec":[""]}},{"listen":"test","script":{"id":"69a85b93-c1e4-4755-acba-786827a2e743","type":"text/javascript","exec":[""]}}]}